odoo10_addon_l10n_de_country_states-10.0.1.0.0-py2.7-nspkg.pth
odoo/addons/l10n_de_country_states/README.rst
odoo/addons/l10n_de_country_states/__init__.py
odoo/addons/l10n_de_country_states/__manifest__.py
odoo/addons/l10n_de_country_states/data/res_country_states.xml
odoo/addons/l10n_de_country_states/i18n/de.po
odoo10_addon_l10n_de_country_states-10.0.1.0.0.dist-info/DESCRIPTION.rst
odoo10_addon_l10n_de_country_states-10.0.1.0.0.dist-info/METADATA
odoo10_addon_l10n_de_country_states-10.0.1.0.0.dist-info/RECORD
odoo10_addon_l10n_de_country_states-10.0.1.0.0.dist-info/WHEEL
odoo10_addon_l10n_de_country_states-10.0.1.0.0.dist-info/metadata.json
odoo10_addon_l10n_de_country_states-10.0.1.0.0.dist-info/namespace_packages.txt
odoo10_addon_l10n_de_country_states-10.0.1.0.0.dist-info/top_level.txt
